{"bn":"chicago/uic/shuttle/","e":[{"n":"phi","v":41.872961,"u":"lat","t":1303650847},{"n":"lambda","v":-87.676435,"u":"lon","t":1303650847},{"n":"phi","v":41.872779,"u":"lat","t":1303650874},{"n":"lambda","v":-87.676433,"u":"lon","t":1303650874},{"n":"phi","v":41.872588,"u":"lat","t":1303650877},{"n":"lambda","v":-87.676427,"u":"lon","t":1303650877},{"n":"phi","v":41.872348,"u":"lat","t":1303650880},{"n":"lambda","v":-87.67642,"u":"lon","t":1303650880},{"n":"phi","v":41.872082,"u":"lat","t":1303650883},{"n":"lambda","v":-87.67639,"u":"lon","t":1303650883},{"n":"phi","v":41.871822,"u":"lat","t":1303650886},{"n":"lambda","v":-87.676371,"u":"lon","t":1303650886},{"n":"phi","v":41.87161,"u":"lat","t":1303650889},{"n":"lambda","v":-87.676361,"u":"lon","t":1303650889},{"n":"phi","v":41.87146,"u":"lat","t":1303650893},{"n":"lambda","v":-87.6762,"u":"lon","t":1303650893},{"n":"phi","v":41.871452,"u":"lat","t":1303650897},{"n":"lambda","v":-87.675871,"u":"lon","t":1303650897},{"n":"phi","v":41.871461,"u":"lat","t":1303650900},{"n":"lambda","v":-87.675584,"u":"lon","t":1303650900},{"n":"phi","v":41.871458,"u":"lat","t":1303650903},{"n":"lambda","v":-87.675325,"u":"lon","t":1303650903},{"n":"phi","v":41.871484,"u":"lat","t":1303650917},{"n":"lambda","v":-87.675073,"u":"lon","t":1303650917},{"n":"phi","v":41.871502,"u":"lat","t":1303650922},{"n":"lambda","v":-87.67476,"u":"lon","t":1303650922},{"n":"phi","v":41.871514,"u":"lat","t":1303650925},{"n":"lambda","v":-87.674498,"u":"lon","t":1303650925},{"n":"phi","v":41.871519,"u":"lat","t":1303650928},{"n":"lambda","v":-87.674227,"u":"lon","t":1303650928},{"n":"phi","v":41.871527,"u":"lat","t":1303650932},{"n":"lambda","v":-87.673949,"u":"lon","t":1303650932},{"n":"phi","v":41.871537,"u":"lat","t":1303650938},{"n":"lambda","v":-87.673659,"u":"lon","t":1303650938},{"n":"phi","v":41.87155,"u":"lat","t":1303650941},{"n":"lambda","v":-87.673416,"u":"lon","t":1303650941},{"n":"phi","v":41.871563,"u":"lat","t":1303650944},{"n":"lambda","v":-87.673121,"u":"lon","t":1303650944},{"n":"phi","v":41.871573,"u":"lat","t":1303650947},{"n":"lambda","v":-87.672801,"u":"lon","t":1303650947},{"n":"phi","v":41.871584,"u":"lat","t":1303650950},{"n":"lambda","v":-87.672474,"u":"lon","t":1303650950},{"n":"phi","v":41.871592,"u":"lat","t":1303650953},{"n":"lambda","v":-87.672151,"u":"lon","t":1303650953},{"n":"phi","v":41.871594,"u":"lat","t":1303650956},{"n":"lambda","v":-87.671828,"u":"lon","t":1303650956},{"n":"phi","v":41.871588,"u":"lat","t":1303650959},{"n":"lambda","v":-87.671482,"u":"lon","t":1303650959},{"n":"phi","v":41.871586,"u":"lat","t":1303650962},{"n":"lambda","v":-87.671144,"u":"lon","t":1303650962},{"n":"phi","v":41.871591,"u":"lat","t":1303650965},{"n":"lambda","v":-87.670818,"u":"lon","t":1303650965},{"n":"phi","v":41.871598,"u":"lat","t":1303650968},{"n":"lambda","v":-87.670482,"u":"lon","t":1303650968},{"n":"phi","v":41.871598,"u":"lat","t":1303650971},{"n":"lambda","v":-87.670142,"u":"lon","t":1303650971},{"n":"phi","v":41.871595,"u":"lat","t":1303650974},{"n":"lambda","v":-87.669809,"u":"lon","t":1303650974},{"n":"phi","v":41.871598,"u":"lat","t":1303650977},{"n":"lambda","v":-87.669511,"u":"lon","t":1303650977},{"n":"phi","v":41.871627,"u":"lat","t":1303650981},{"n":"lambda","v":-87.669247,"u":"lon","t":1303650981},{"n":"phi","v":41.87149,"u":"lat","t":1303650988},{"n":"lambda","v":-87.66906,"u":"lon","t":1303650988},{"n":"phi","v":41.871275,"u":"lat","t":1303650992},{"n":"lambda","v":-87.669047,"u":"lon","t":1303650992},{"n":"phi","v":41.871076,"u":"lat","t":1303650995},{"n":"lambda","v":-87.669032,"u":"lon","t":1303650995},{"n":"phi","v":41.870861,"u":"lat","t":1303650998},{"n":"lambda","v":-87.669027,"u":"lon","t":1303650998},{"n":"phi","v":41.870638,"u":"lat","t":1303651001},{"n":"lambda","v":-87.669017,"u":"lon","t":1303651001},{"n":"phi","v":41.870421,"u":"lat","t":1303651004},{"n":"lambda","v":-87.669007,"u":"lon","t":1303651004},{"n":"phi","v":41.870203,"u":"lat","t":1303651007},{"n":"lambda","v":-87.669001,"u":"lon","t":1303651007},{"n":"phi","v":41.869976,"u":"lat","t":1303651010},{"n":"lambda","v":-87.669002,"u":"lon","t":1303651010},{"n":"phi","v":41.869755,"u":"lat","t":1303651013},{"n":"lambda","v":-87.669002,"u":"lon","t":1303651013},{"n":"phi","v":41.869553,"u":"lat","t":1303651016},{"n":"lambda","v":-87.669002,"u":"lon","t":1303651016},{"n":"phi","v":41.869359,"u":"lat","t":1303651021},{"n":"lambda","v":-87.668995,"u":"lon","t":1303651021},{"n":"phi","v":41.869229,"u":"lat","t":1303651027},{"n":"lambda","v":-87.6688,"u":"lon","t":1303651027},{"n":"phi","v":41.869241,"u":"lat","t":1303651031},{"n":"lambda","v":-87.668483,"u":"lon","t":1303651031},{"n":"phi","v":41.869255,"u":"lat","t":1303651034},{"n":"lambda","v":-87.66818,"u":"lon","t":1303651034},{"n":"phi","v":41.869267,"u":"lat","t":1303651037},{"n":"lambda","v":-87.667862,"u":"lon","t":1303651037},{"n":"phi","v":41.869275,"u":"lat","t":1303651040},{"n":"lambda","v":-87.667544,"u":"lon","t":1303651040},{"n":"phi","v":41.869268,"u":"lat","t":1303651043},{"n":"lambda","v":-87.667219,"u":"lon","t":1303651043},{"n":"phi","v":41.869263,"u":"lat","t":1303651046},{"n":"lambda","v":-87.666917,"u":"lon","t":1303651046},{"n":"phi","v":41.869248,"u":"lat","t":1303651051},{"n":"lambda","v":-87.666658,"u":"lon","t":1303651051},{"n":"phi","v":41.869252,"u":"lat","t":1303651064},{"n":"lambda","v":-87.666344,"u":"lon","t":1303651064},{"n":"phi","v":41.869262,"u":"lat","t":1303651067},{"n":"lambda","v":-87.666079,"u":"lon","t":1303651067},{"n":"phi","v":41.869277,"u":"lat","t":1303651070},{"n":"lambda","v":-87.665773,"u":"lon","t":1303651070},{"n":"phi","v":41.869288,"u":"lat","t":1303651073},{"n":"lambda","v":-87.665449,"u":"lon","t":1303651073},{"n":"phi","v":41.869291,"u":"lat","t":1303651076},{"n":"lambda","v":-87.665122,"u":"lon","t":1303651076},{"n":"phi","v":41.869294,"u":"lat","t":1303651079},{"n":"lambda","v":-87.664807,"u":"lon","t":1303651079},{"n":"phi","v":41.869297,"u":"lat","t":1303651082},{"n":"lambda","v":-87.664518,"u":"lon","t":1303651082},{"n":"phi","v":41.869301,"u":"lat","t":1303651086},{"n":"lambda","v":-87.66424,"u":"lon","t":1303651086},{"n":"phi","v":41.869317,"u":"lat","t":1303651092},{"n":"lambda","v":-87.663993,"u":"lon","t":1303651092},{"n":"phi","v":41.869334,"u":"lat","t":1303651096},{"n":"lambda","v":-87.663664,"u":"lon","t":1303651096},{"n":"phi","v":41.86934,"u":"lat","t":1303651099},{"n":"lambda","v":-87.663367,"u":"lon","t":1303651099},{"n":"phi","v":41.869348,"u":"lat","t":1303651102},{"n":"lambda","v":-87.663045,"u":"lon","t":1303651102},{"n":"phi","v":41.869357,"u":"lat","t":1303651105},{"n":"lambda","v":-87.662713,"u":"lon","t":1303651105},{"n":"phi","v":41.869363,"u":"lat","t":1303651108},{"n":"lambda","v":-87.662381,"u":"lon","t":1303651108},{"n":"phi","v":41.869368,"u":"lat","t":1303651111},{"n":"lambda","v":-87.662056,"u":"lon","t":1303651111},{"n":"phi","v":41.869373,"u":"lat","t":1303651114},{"n":"lambda","v":-87.661717,"u":"lon","t":1303651114},{"n":"phi","v":41.869386,"u":"lat","t":1303651117},{"n":"lambda","v":-87.661368,"u":"lon","t":1303651117},{"n":"phi","v":41.869393,"u":"lat","t":1303651119},{"n":"lambda","v":-87.661126,"u":"lon","t":1303651119},{"n":"phi","v":41.869399,"u":"lat","t":1303651121},{"n":"lambda","v":-87.660874,"u":"lon","t":1303651121},{"n":"phi","v":41.869404,"u":"lat","t":1303651123},{"n":"lambda","v":-87.660617,"u":"lon","t":1303651123},{"n":"phi","v":41.869408,"u":"lat","t":1303651125},{"n":"lambda","v":-87.660352,"u":"lon","t":1303651125},{"n":"phi","v":41.86941,"u":"lat","t":1303651127},{"n":"lambda","v":-87.660086,"u":"lon","t":1303651127},{"n":"phi","v":41.869413,"u":"lat","t":1303651129},{"n":"lambda","v":-87.659815,"u":"lon","t":1303651129},{"n":"phi","v":41.869417,"u":"lat","t":1303651131},{"n":"lambda","v":-87.659539,"u":"lon","t":1303651131},{"n":"phi","v":41.869413,"u":"lat","t":1303651133},{"n":"lambda","v":-87.659258,"u":"lon","t":1303651133},{"n":"phi","v":41.869415,"u":"lat","t":1303651135},{"n":"lambda","v":-87.658989,"u":"lon","t":1303651135},{"n":"phi","v":41.869412,"u":"lat","t":1303651137},{"n":"lambda","v":-87.658728,"u":"lon","t":1303651137},{"n":"phi","v":41.86941,"u":"lat","t":1303651139},{"n":"lambda","v":-87.658466,"u":"lon","t":1303651139},{"n":"phi","v":41.869409,"u":"lat","t":1303651141},{"n":"lambda","v":-87.658211,"u":"lon","t":1303651141},{"n":"phi","v":41.869412,"u":"lat","t":1303651144},{"n":"lambda","v":-87.657858,"u":"lon","t":1303651144},{"n":"phi","v":41.869418,"u":"lat","t":1303651147},{"n":"lambda","v":-87.657521,"u":"lon","t":1303651147},{"n":"phi","v":41.869426,"u":"lat","t":1303651150},{"n":"lambda","v":-87.657218,"u":"lon","t":1303651150},{"n":"phi","v":41.869431,"u":"lat","t":1303651154},{"n":"lambda","v":-87.656937,"u":"lon","t":1303651154},{"n":"phi","v":41.869508,"u":"lat","t":1303651180},{"n":"lambda","v":-87.656708,"u":"lon","t":1303651180},{"n":"phi","v":41.869693,"u":"lat","t":1303651184},{"n":"lambda","v":-87.6567,"u":"lon","t":1303651184},{"n":"phi","v":41.869894,"u":"lat","t":1303651187},{"n":"lambda","v":-87.656711,"u":"lon","t":1303651187},{"n":"phi","v":41.87012,"u":"lat","t":1303651190},{"n":"lambda","v":-87.656729,"u":"lon","t":1303651190},{"n":"phi","v":41.870369,"u":"lat","t":1303651193},{"n":"lambda","v":-87.656738,"u":"lon","t":1303651193},{"n":"phi","v":41.870622,"u":"lat","t":1303651196},{"n":"lambda","v":-87.656747,"u":"lon","t":1303651196},{"n":"phi","v":41.870882,"u":"lat","t":1303651199},{"n":"lambda","v":-87.656757,"u":"lon","t":1303651199},{"n":"phi","v":41.871143,"u":"lat","t":1303651202},{"n":"lambda","v":-87.656769,"u":"lon","t":1303651202},{"n":"phi","v":41.871395,"u":"lat","t":1303651205},{"n":"lambda","v":-87.656771,"u":"lon","t":1303651205},{"n":"phi","v":41.871624,"u":"lat","t":1303651208},{"n":"lambda","v":-87.65676,"u":"lon","t":1303651208},{"n":"phi","v":41.871834,"u":"lat","t":1303651211},{"n":"lambda","v":-87.656747,"u":"lon","t":1303651211},{"n":"phi","v":41.872055,"u":"lat","t":1303651215},{"n":"lambda","v":-87.656745,"u":"lon","t":1303651215},{"n":"phi","v":41.872237,"u":"lat","t":1303651221},{"n":"lambda","v":-87.656748,"u":"lon","t":1303651221},{"n":"phi","v":41.87246,"u":"lat","t":1303651225},{"n":"lambda","v":-87.656747,"u":"lon","t":1303651225},{"n":"phi","v":41.872661,"u":"lat","t":1303651228},{"n":"lambda","v":-87.656737,"u":"lon","t":1303651228},{"n":"phi","v":41.872869,"u":"lat","t":1303651231},{"n":"lambda","v":-87.656725,"u":"lon","t":1303651231},{"n":"phi","v":41.873086,"u":"lat","t":1303651234},{"n":"lambda","v":-87.656708,"u":"lon","t":1303651234},{"n":"phi","v":41.873308,"u":"lat","t":1303651237},{"n":"lambda","v":-87.656697,"u":"lon","t":1303651237},{"n":"phi","v":41.873541,"u":"lat","t":1303651240},{"n":"lambda","v":-87.656699,"u":"lon","t":1303651240},{"n":"phi","v":41.873765,"u":"lat","t":1303651243},{"n":"lambda","v":-87.656704,"u":"lon","t":1303651243},{"n":"phi","v":41.87396,"u":"lat","t":1303651246},{"n":"lambda","v":-87.656705,"u":"lon","t":1303651246},{"n":"phi","v":41.874169,"u":"lat","t":1303651250},{"n":"lambda","v":-87.656701,"u":"lon","t":1303651250},{"n":"phi","v":41.874237,"u":"lat","t":1303651255},{"n":"lambda","v":-87.656407,"u":"lon","t":1303651255},{"n":"phi","v":41.874241,"u":"lat","t":1303651259},{"n":"lambda","v":-87.656081,"u":"lon","t":1303651259},{"n":"phi","v":41.874243,"u":"lat","t":1303651262},{"n":"lambda","v":-87.655797,"u":"lon","t":1303651262},{"n":"phi","v":41.874251,"u":"lat","t":1303651265},{"n":"lambda","v":-87.655495,"u":"lon","t":1303651265},{"n":"phi","v":41.874256,"u":"lat","t":1303651268},{"n":"lambda","v":-87.655196,"u":"lon","t":1303651268},{"n":"phi","v":41.874258,"u":"lat","t":1303651271},{"n":"lambda","v":-87.654889,"u":"lon","t":1303651271},{"n":"phi","v":41.874259,"u":"lat","t":1303651274},{"n":"lambda","v":-87.654576,"u":"lon","t":1303651274},{"n":"phi","v":41.874263,"u":"lat","t":1303651277},{"n":"lambda","v":-87.654259,"u":"lon","t":1303651277},{"n":"phi","v":41.87427,"u":"lat","t":1303651280},{"n":"lambda","v":-87.653949,"u":"lon","t":1303651280},{"n":"phi","v":41.874276,"u":"lat","t":1303651283},{"n":"lambda","v":-87.653641,"u":"lon","t":1303651283},{"n":"phi","v":41.874282,"u":"lat","t":1303651286},{"n":"lambda","v":-87.653344,"u":"lon","t":1303651286},{"n":"phi","v":41.87429,"u":"lat","t":1303651289},{"n":"lambda","v":-87.653052,"u":"lon","t":1303651289},{"n":"phi","v":41.874298,"u":"lat","t":1303651292},{"n":"lambda","v":-87.652758,"u":"lon","t":1303651292},{"n":"phi","v":41.874301,"u":"lat","t":1303651295},{"n":"lambda","v":-87.652466,"u":"lon","t":1303651295},{"n":"phi","v":41.874306,"u":"lat","t":1303651298},{"n":"lambda","v":-87.652188,"u":"lon","t":1303651298},{"n":"phi","v":41.874316,"u":"lat","t":1303651301},{"n":"lambda","v":-87.651904,"u":"lon","t":1303651301},{"n":"phi","v":41.874326,"u":"lat","t":1303651304},{"n":"lambda","v":-87.651607,"u":"lon","t":1303651304},{"n":"phi","v":41.874332,"u":"lat","t":1303651307},{"n":"lambda","v":-87.651288,"u":"lon","t":1303651307},{"n":"phi","v":41.874335,"u":"lat","t":1303651310},{"n":"lambda","v":-87.65096,"u":"lon","t":1303651310},{"n":"phi","v":41.874341,"u":"lat","t":1303651313},{"n":"lambda","v":-87.650645,"u":"lon","t":1303651313},{"n":"phi","v":41.874352,"u":"lat","t":1303651316},{"n":"lambda","v":-87.650328,"u":"lon","t":1303651316},{"n":"phi","v":41.874357,"u":"lat","t":1303651319},{"n":"lambda","v":-87.650012,"u":"lon","t":1303651319},{"n":"phi","v":41.874366,"u":"lat","t":1303651322},{"n":"lambda","v":-87.649692,"u":"lon","t":1303651322},{"n":"phi","v":41.874386,"u":"lat","t":1303651325},{"n":"lambda","v":-87.649372,"u":"lon","t":1303651325}]}