{"bn":"chicago/uic/shuttle/","e":[{"n":"phi","v":41.865743,"u":"lat","t":1303945284},{"n":"lambda","v":-87.646907,"u":"lon","t":1303945284},{"n":"phi","v":41.865557,"u":"lat","t":1303945301},{"n":"lambda","v":-87.646835,"u":"lon","t":1303945301},{"n":"phi","v":41.865367,"u":"lat","t":1303945327},{"n":"lambda","v":-87.646806,"u":"lon","t":1303945327},{"n":"phi","v":41.865187,"u":"lat","t":1303945334},{"n":"lambda","v":-87.646802,"u":"lon","t":1303945334},{"n":"phi","v":41.865003,"u":"lat","t":1303945355},{"n":"lambda","v":-87.646827,"u":"lon","t":1303945355},{"n":"phi","v":41.864822,"u":"lat","t":1303945359},{"n":"lambda","v":-87.646851,"u":"lon","t":1303945359},{"n":"phi","v":41.864591,"u":"lat","t":1303945363},{"n":"lambda","v":-87.646843,"u":"lon","t":1303945363},{"n":"phi","v":41.864382,"u":"lat","t":1303945366},{"n":"lambda","v":-87.646839,"u":"lon","t":1303945366},{"n":"phi","v":41.864164,"u":"lat","t":1303945369},{"n":"lambda","v":-87.646842,"u":"lon","t":1303945369},{"n":"phi","v":41.863943,"u":"lat","t":1303945372},{"n":"lambda","v":-87.646836,"u":"lon","t":1303945372},{"n":"phi","v":41.863698,"u":"lat","t":1303945375},{"n":"lambda","v":-87.646844,"u":"lon","t":1303945375},{"n":"phi","v":41.863435,"u":"lat","t":1303945378},{"n":"lambda","v":-87.646847,"u":"lon","t":1303945378},{"n":"phi","v":41.863175,"u":"lat","t":1303945381},{"n":"lambda","v":-87.646849,"u":"lon","t":1303945381},{"n":"phi","v":41.86294,"u":"lat","t":1303945384},{"n":"lambda","v":-87.64685,"u":"lon","t":1303945384},{"n":"phi","v":41.862748,"u":"lat","t":1303945387},{"n":"lambda","v":-87.646843,"u":"lon","t":1303945387},{"n":"phi","v":41.862566,"u":"lat","t":1303945391},{"n":"lambda","v":-87.646847,"u":"lon","t":1303945391},{"n":"phi","v":41.862385,"u":"lat","t":1303945399},{"n":"lambda","v":-87.64692,"u":"lon","t":1303945399},{"n":"phi","v":41.8624,"u":"lat","t":1303945404},{"n":"lambda","v":-87.647247,"u":"lon","t":1303945404},{"n":"phi","v":41.8624,"u":"lat","t":1303945407},{"n":"lambda","v":-87.647552,"u":"lon","t":1303945407},{"n":"phi","v":41.862383,"u":"lat","t":1303945410},{"n":"lambda","v":-87.647873,"u":"lon","t":1303945410},{"n":"phi","v":41.862368,"u":"lat","t":1303945413},{"n":"lambda","v":-87.648205,"u":"lon","t":1303945413},{"n":"phi","v":41.862342,"u":"lat","t":1303945416},{"n":"lambda","v":-87.648498,"u":"lon","t":1303945416},{"n":"phi","v":41.862326,"u":"lat","t":1303945421},{"n":"lambda","v":-87.648757,"u":"lon","t":1303945421},{"n":"phi","v":41.862348,"u":"lat","t":1303945425},{"n":"lambda","v":-87.649076,"u":"lon","t":1303945425},{"n":"phi","v":41.862352,"u":"lat","t":1303945427},{"n":"lambda","v":-87.649318,"u":"lon","t":1303945427},{"n":"phi","v":41.862347,"u":"lat","t":1303945429},{"n":"lambda","v":-87.649578,"u":"lon","t":1303945429},{"n":"phi","v":41.862344,"u":"lat","t":1303945431},{"n":"lambda","v":-87.649828,"u":"lon","t":1303945431},{"n":"phi","v":41.862357,"u":"lat","t":1303945434},{"n":"lambda","v":-87.650156,"u":"lon","t":1303945434},{"n":"phi","v":41.862378,"u":"lat","t":1303945437},{"n":"lambda","v":-87.650434,"u":"lon","t":1303945437},{"n":"phi","v":41.862357,"u":"lat","t":1303945442},{"n":"lambda","v":-87.65069,"u":"lon","t":1303945442},{"n":"phi","v":41.862501,"u":"lat","t":1303945456},{"n":"lambda","v":-87.650867,"u":"lon","t":1303945456},{"n":"phi","v":41.862785,"u":"lat","t":1303945462},{"n":"lambda","v":-87.650863,"u":"lon","t":1303945462},{"n":"phi","v":41.863011,"u":"lat","t":1303945466},{"n":"lambda","v":-87.650877,"u":"lon","t":1303945466},{"n":"phi","v":41.863235,"u":"lat","t":1303945470},{"n":"lambda","v":-87.650898,"u":"lon","t":1303945470},{"n":"phi","v":41.86346,"u":"lat","t":1303945475},{"n":"lambda","v":-87.650915,"u":"lon","t":1303945475},{"n":"phi","v":41.86365,"u":"lat","t":1303945478},{"n":"lambda","v":-87.650925,"u":"lon","t":1303945478},{"n":"phi","v":41.863913,"u":"lat","t":1303945481},{"n":"lambda","v":-87.650947,"u":"lon","t":1303945481},{"n":"phi","v":41.864093,"u":"lat","t":1303945483},{"n":"lambda","v":-87.650963,"u":"lon","t":1303945483},{"n":"phi","v":41.864343,"u":"lat","t":1303945486},{"n":"lambda","v":-87.650965,"u":"lon","t":1303945486},{"n":"phi","v":41.864528,"u":"lat","t":1303945489},{"n":"lambda","v":-87.650969,"u":"lon","t":1303945489},{"n":"phi","v":41.864708,"u":"lat","t":1303945495},{"n":"lambda","v":-87.651003,"u":"lon","t":1303945495},{"n":"phi","v":41.864915,"u":"lat","t":1303945499},{"n":"lambda","v":-87.651013,"u":"lon","t":1303945499},{"n":"phi","v":41.865153,"u":"lat","t":1303945502},{"n":"lambda","v":-87.651031,"u":"lon","t":1303945502},{"n":"phi","v":41.865376,"u":"lat","t":1303945504},{"n":"lambda","v":-87.651037,"u":"lon","t":1303945504},{"n":"phi","v":41.865603,"u":"lat","t":1303945506},{"n":"lambda","v":-87.651049,"u":"lon","t":1303945506},{"n":"phi","v":41.865818,"u":"lat","t":1303945508},{"n":"lambda","v":-87.651056,"u":"lon","t":1303945508},{"n":"phi","v":41.866018,"u":"lat","t":1303945510},{"n":"lambda","v":-87.651059,"u":"lon","t":1303945510},{"n":"phi","v":41.866206,"u":"lat","t":1303945512},{"n":"lambda","v":-87.651067,"u":"lon","t":1303945512},{"n":"phi","v":41.866463,"u":"lat","t":1303945515},{"n":"lambda","v":-87.651078,"u":"lon","t":1303945515},{"n":"phi","v":41.866686,"u":"lat","t":1303945519},{"n":"lambda","v":-87.651094,"u":"lon","t":1303945519},{"n":"phi","v":41.866874,"u":"lat","t":1303945538},{"n":"lambda","v":-87.651111,"u":"lon","t":1303945538},{"n":"phi","v":41.867065,"u":"lat","t":1303945556},{"n":"lambda","v":-87.65115,"u":"lon","t":1303945556},{"n":"phi","v":41.867165,"u":"lat","t":1303945560},{"n":"lambda","v":-87.651408,"u":"lon","t":1303945560},{"n":"phi","v":41.867164,"u":"lat","t":1303945563},{"n":"lambda","v":-87.65173,"u":"lon","t":1303945563},{"n":"phi","v":41.867155,"u":"lat","t":1303945566},{"n":"lambda","v":-87.65209,"u":"lon","t":1303945566},{"n":"phi","v":41.867148,"u":"lat","t":1303945569},{"n":"lambda","v":-87.652418,"u":"lon","t":1303945569},{"n":"phi","v":41.867139,"u":"lat","t":1303945573},{"n":"lambda","v":-87.652695,"u":"lon","t":1303945573},{"n":"phi","v":41.867124,"u":"lat","t":1303945578},{"n":"lambda","v":-87.652963,"u":"lon","t":1303945578},{"n":"phi","v":41.867112,"u":"lat","t":1303945582},{"n":"lambda","v":-87.653253,"u":"lon","t":1303945582},{"n":"phi","v":41.86711,"u":"lat","t":1303945585},{"n":"lambda","v":-87.653524,"u":"lon","t":1303945585},{"n":"phi","v":41.867111,"u":"lat","t":1303945588},{"n":"lambda","v":-87.653841,"u":"lon","t":1303945588},{"n":"phi","v":41.867112,"u":"lat","t":1303945590},{"n":"lambda","v":-87.654084,"u":"lon","t":1303945590},{"n":"phi","v":41.8671,"u":"lat","t":1303945592},{"n":"lambda","v":-87.654326,"u":"lon","t":1303945592},{"n":"phi","v":41.867086,"u":"lat","t":1303945595},{"n":"lambda","v":-87.654664,"u":"lon","t":1303945595},{"n":"phi","v":41.867083,"u":"lat","t":1303945598},{"n":"lambda","v":-87.655011,"u":"lon","t":1303945598},{"n":"phi","v":41.867092,"u":"lat","t":1303945600},{"n":"lambda","v":-87.655274,"u":"lon","t":1303945600},{"n":"phi","v":41.867099,"u":"lat","t":1303945602},{"n":"lambda","v":-87.655542,"u":"lon","t":1303945602},{"n":"phi","v":41.8671,"u":"lat","t":1303945604},{"n":"lambda","v":-87.655802,"u":"lon","t":1303945604},{"n":"phi","v":41.867095,"u":"lat","t":1303945606},{"n":"lambda","v":-87.656057,"u":"lon","t":1303945606},{"n":"phi","v":41.867105,"u":"lat","t":1303945609},{"n":"lambda","v":-87.656372,"u":"lon","t":1303945609},{"n":"phi","v":41.86714,"u":"lat","t":1303945613},{"n":"lambda","v":-87.656644,"u":"lon","t":1303945613},{"n":"phi","v":41.867332,"u":"lat","t":1303945618},{"n":"lambda","v":-87.65668,"u":"lon","t":1303945618},{"n":"phi","v":41.867514,"u":"lat","t":1303945621},{"n":"lambda","v":-87.656703,"u":"lon","t":1303945621},{"n":"phi","v":41.867748,"u":"lat","t":1303945624},{"n":"lambda","v":-87.656728,"u":"lon","t":1303945624},{"n":"phi","v":41.868012,"u":"lat","t":1303945627},{"n":"lambda","v":-87.656744,"u":"lon","t":1303945627},{"n":"phi","v":41.868202,"u":"lat","t":1303945629},{"n":"lambda","v":-87.656756,"u":"lon","t":1303945629},{"n":"phi","v":41.868404,"u":"lat","t":1303945631},{"n":"lambda","v":-87.656769,"u":"lon","t":1303945631},{"n":"phi","v":41.868607,"u":"lat","t":1303945633},{"n":"lambda","v":-87.656783,"u":"lon","t":1303945633},{"n":"phi","v":41.868799,"u":"lat","t":1303945635},{"n":"lambda","v":-87.656796,"u":"lon","t":1303945635},{"n":"phi","v":41.869038,"u":"lat","t":1303945638},{"n":"lambda","v":-87.656798,"u":"lon","t":1303945638},{"n":"phi","v":41.869242,"u":"lat","t":1303945642},{"n":"lambda","v":-87.656793,"u":"lon","t":1303945642},{"n":"phi","v":41.869441,"u":"lat","t":1303945662},{"n":"lambda","v":-87.656768,"u":"lon","t":1303945662},{"n":"phi","v":41.869662,"u":"lat","t":1303945667},{"n":"lambda","v":-87.656787,"u":"lon","t":1303945667},{"n":"phi","v":41.86986,"u":"lat","t":1303945670},{"n":"lambda","v":-87.656775,"u":"lon","t":1303945670},{"n":"phi","v":41.870063,"u":"lat","t":1303945673},{"n":"lambda","v":-87.656785,"u":"lon","t":1303945673},{"n":"phi","v":41.870273,"u":"lat","t":1303945676},{"n":"lambda","v":-87.656803,"u":"lon","t":1303945676},{"n":"phi","v":41.870469,"u":"lat","t":1303945679},{"n":"lambda","v":-87.656801,"u":"lon","t":1303945679},{"n":"phi","v":41.870681,"u":"lat","t":1303945684},{"n":"lambda","v":-87.656804,"u":"lon","t":1303945684},{"n":"phi","v":41.870868,"u":"lat","t":1303945687},{"n":"lambda","v":-87.656807,"u":"lon","t":1303945687},{"n":"phi","v":41.871056,"u":"lat","t":1303945690},{"n":"lambda","v":-87.656816,"u":"lon","t":1303945690},{"n":"phi","v":41.871255,"u":"lat","t":1303945694},{"n":"lambda","v":-87.656848,"u":"lon","t":1303945694},{"n":"phi","v":41.871447,"u":"lat","t":1303945698},{"n":"lambda","v":-87.656846,"u":"lon","t":1303945698},{"n":"phi","v":41.871665,"u":"lat","t":1303945702},{"n":"lambda","v":-87.656812,"u":"lon","t":1303945702},{"n":"phi","v":41.871891,"u":"lat","t":1303945706},{"n":"lambda","v":-87.656813,"u":"lon","t":1303945706},{"n":"phi","v":41.872102,"u":"lat","t":1303945713},{"n":"lambda","v":-87.656805,"u":"lon","t":1303945713},{"n":"phi","v":41.872316,"u":"lat","t":1303945718},{"n":"lambda","v":-87.656824,"u":"lon","t":1303945718},{"n":"phi","v":41.872529,"u":"lat","t":1303945722},{"n":"lambda","v":-87.656795,"u":"lon","t":1303945722},{"n":"phi","v":41.872773,"u":"lat","t":1303945726},{"n":"lambda","v":-87.656764,"u":"lon","t":1303945726},{"n":"phi","v":41.872991,"u":"lat","t":1303945729},{"n":"lambda","v":-87.656742,"u":"lon","t":1303945729},{"n":"phi","v":41.873196,"u":"lat","t":1303945732},{"n":"lambda","v":-87.656739,"u":"lon","t":1303945732},{"n":"phi","v":41.87338,"u":"lat","t":1303945735},{"n":"lambda","v":-87.656744,"u":"lon","t":1303945735},{"n":"phi","v":41.873587,"u":"lat","t":1303945739},{"n":"lambda","v":-87.656767,"u":"lon","t":1303945739},{"n":"phi","v":41.873787,"u":"lat","t":1303945744},{"n":"lambda","v":-87.656798,"u":"lon","t":1303945744},{"n":"phi","v":41.873991,"u":"lat","t":1303945749},{"n":"lambda","v":-87.656783,"u":"lon","t":1303945749},{"n":"phi","v":41.874141,"u":"lat","t":1303945754},{"n":"lambda","v":-87.656548,"u":"lon","t":1303945754},{"n":"phi","v":41.874213,"u":"lat","t":1303945758},{"n":"lambda","v":-87.65625,"u":"lon","t":1303945758},{"n":"phi","v":41.874222,"u":"lat","t":1303945761},{"n":"lambda","v":-87.655948,"u":"lon","t":1303945761},{"n":"phi","v":41.87423,"u":"lat","t":1303945764},{"n":"lambda","v":-87.655629,"u":"lon","t":1303945764},{"n":"phi","v":41.874242,"u":"lat","t":1303945767},{"n":"lambda","v":-87.655287,"u":"lon","t":1303945767},{"n":"phi","v":41.874257,"u":"lat","t":1303945770},{"n":"lambda","v":-87.65492,"u":"lon","t":1303945770},{"n":"phi","v":41.874271,"u":"lat","t":1303945773},{"n":"lambda","v":-87.654524,"u":"lon","t":1303945773},{"n":"phi","v":41.874277,"u":"lat","t":1303945775},{"n":"lambda","v":-87.654258,"u":"lon","t":1303945775},{"n":"phi","v":41.874282,"u":"lat","t":1303945777},{"n":"lambda","v":-87.653996,"u":"lon","t":1303945777},{"n":"phi","v":41.874288,"u":"lat","t":1303945779},{"n":"lambda","v":-87.653734,"u":"lon","t":1303945779},{"n":"phi","v":41.874289,"u":"lat","t":1303945781},{"n":"lambda","v":-87.653471,"u":"lon","t":1303945781},{"n":"phi","v":41.874292,"u":"lat","t":1303945783},{"n":"lambda","v":-87.653214,"u":"lon","t":1303945783},{"n":"phi","v":41.874293,"u":"lat","t":1303945785},{"n":"lambda","v":-87.652967,"u":"lon","t":1303945785},{"n":"phi","v":41.874292,"u":"lat","t":1303945788},{"n":"lambda","v":-87.65264,"u":"lon","t":1303945788},{"n":"phi","v":41.874296,"u":"lat","t":1303945791},{"n":"lambda","v":-87.652341,"u":"lon","t":1303945791},{"n":"phi","v":41.8743,"u":"lat","t":1303945794},{"n":"lambda","v":-87.652089,"u":"lon","t":1303945794},{"n":"phi","v":41.87431,"u":"lat","t":1303945797},{"n":"lambda","v":-87.651823,"u":"lon","t":1303945797},{"n":"phi","v":41.874312,"u":"lat","t":1303945800},{"n":"lambda","v":-87.651569,"u":"lon","t":1303945800},{"n":"phi","v":41.874308,"u":"lat","t":1303945804},{"n":"lambda","v":-87.651292,"u":"lon","t":1303945804},{"n":"phi","v":41.874322,"u":"lat","t":1303945808},{"n":"lambda","v":-87.650987,"u":"lon","t":1303945808},{"n":"phi","v":41.874318,"u":"lat","t":1303945811},{"n":"lambda","v":-87.650695,"u":"lon","t":1303945811},{"n":"phi","v":41.874311,"u":"lat","t":1303945814},{"n":"lambda","v":-87.650387,"u":"lon","t":1303945814},{"n":"phi","v":41.874319,"u":"lat","t":1303945817},{"n":"lambda","v":-87.650098,"u":"lon","t":1303945817},{"n":"phi","v":41.874325,"u":"lat","t":1303945820},{"n":"lambda","v":-87.649853,"u":"lon","t":1303945820},{"n":"phi","v":41.874331,"u":"lat","t":1303945825},{"n":"lambda","v":-87.649609,"u":"lon","t":1303945825},{"n":"phi","v":41.874357,"u":"lat","t":1303945847},{"n":"lambda","v":-87.649313,"u":"lon","t":1303945847},{"n":"phi","v":41.874359,"u":"lat","t":1303945850},{"n":"lambda","v":-87.649065,"u":"lon","t":1303945850},{"n":"phi","v":41.874351,"u":"lat","t":1303945853},{"n":"lambda","v":-87.648769,"u":"lon","t":1303945853},{"n":"phi","v":41.874345,"u":"lat","t":1303945857},{"n":"lambda","v":-87.648508,"u":"lon","t":1303945857}]}